archivepodcast/__init__.py
archivepodcast/__main__.py
archivepodcast/archiver/__init__.py
archivepodcast/archiver/podcast_archiver.py
archivepodcast/archiver/webpage_renderer.py
archivepodcast/archiver/webpages.py
archivepodcast/blueprints/__init__.py
archivepodcast/blueprints/api.py
archivepodcast/blueprints/content.py
archivepodcast/blueprints/rss.py
archivepodcast/blueprints/static.py
archivepodcast/blueprints/webpages.py
archivepodcast/config.py
archivepodcast/constants.py
archivepodcast/downloader/__init__.py
archivepodcast/downloader/asset_downloader.py
archivepodcast/downloader/constants.py
archivepodcast/downloader/downloader.py
archivepodcast/downloader/helpers.py
archivepodcast/instances/__init__.py
archivepodcast/instances/config.py
archivepodcast/instances/health.py
archivepodcast/instances/path_cache.py
archivepodcast/instances/path_helper.py
archivepodcast/instances/podcast_archiver.py
archivepodcast/instances/profiler.py
archivepodcast/lambda_handler.py
archivepodcast/static/clipboard.js
archivepodcast/static/favicon.ico
archivepodcast/static/filelist.js
archivepodcast/static/fonts/fira-code-v12-latin-500.woff2
archivepodcast/static/fonts/fira-code-v12-latin-600.woff2
archivepodcast/static/fonts/fira-code-v12-latin-700.woff2
archivepodcast/static/fonts/noto-sans-display-latin-500.woff2
archivepodcast/static/fonts/noto-sans-display-latin-500italic.woff2
archivepodcast/static/health.js
archivepodcast/static/main.css
archivepodcast/static/transparent.png
archivepodcast/static/webplayer.js
archivepodcast/templates/_head_meta.html.j2
archivepodcast/templates/about.html.j2
archivepodcast/templates/error.html.j2
archivepodcast/templates/filelist.html.j2
archivepodcast/templates/guide.html.j2
archivepodcast/templates/health.html.j2
archivepodcast/templates/index.html.j2
archivepodcast/templates/webplayer.html.j2
archivepodcast/utils/__init__.py
archivepodcast/utils/file_cache.py
archivepodcast/utils/health.py
archivepodcast/utils/log_messages.py
archivepodcast-1.5.9.dist-info/WHEEL
archivepodcast-1.5.9.dist-info/entry_points.txt
archivepodcast-1.5.9.dist-info/METADATA
archivepodcast-1.5.9.dist-info/RECORD
