Metadata-Version: 2.3
Name: archivepodcast
Version: 1.5.9
Summary: Flask webapp that will archive a podcast from a RSS feed. It will download the episodes and re-host them.
Author: Kieran Gee
Author-email: Kieran Gee <kieran.lost.the.game@gmail.com>
Requires-Dist: flask[async]>=3.1,<4
Requires-Dist: aiobotocore>=2.25.2
Requires-Dist: aiohttp>=3.13.2
Requires-Dist: jinja2>=3.1,<4
Requires-Dist: lxml>=5,<5.4
Requires-Dist: markdown>=3.10
Requires-Dist: psutil>=7.1.3
Requires-Dist: pydantic>=2.12
Requires-Dist: pydantic-settings>=2.12
Requires-Dist: python-magic>=0.4
Requires-Dist: rich>=14.2.0
Requires-Dist: typed-ffmpeg>=3.7
Requires-Dist: waitress>=3.0
Requires-Dist: sphinx ; extra == 'docs'
Requires-Dist: myst-parser ; extra == 'docs'
Requires-Dist: sphinx-rtd-theme ; extra == 'docs'
Requires-Dist: ruff ; extra == 'lint'
Requires-Dist: aiomonitor ; extra == 'profile'
Requires-Dist: pytest>=9.0 ; extra == 'test'
Requires-Dist: pytest-cov ; extra == 'test'
Requires-Dist: pytest-mock ; extra == 'test'
Requires-Dist: pytest-random-order ; extra == 'test'
Requires-Dist: detect-test-pollution ; extra == 'test'
Requires-Dist: types-aiobotocore-s3 ; extra == 'test'
Requires-Dist: pytest-asyncio ; extra == 'test'
Requires-Dist: pytest-socket>=0.7.0 ; extra == 'test'
Requires-Dist: mypy ; extra == 'type'
Requires-Dist: ty ; extra == 'type'
Requires-Dist: types-lxml ; extra == 'type'
Requires-Dist: types-psutil ; extra == 'type'
Requires-Dist: types-markdown ; extra == 'type'
Requires-Dist: botocore-stubs ; extra == 'type'
Requires-Dist: types-aiobotocore ; extra == 'type'
Requires-Dist: types-aiobotocore-s3 ; extra == 'type'
Requires-Dist: aws-lambda-powertools ; extra == 'type'
Requires-Python: >=3.11, <3.15
Project-URL: docs, https://archivepodcast.readthedocs.io/
Project-URL: repository, https://github.com/kism/archivepodcast
Provides-Extra: docs
Provides-Extra: lint
Provides-Extra: profile
Provides-Extra: test
Provides-Extra: type
